starfysh/AA.py
starfysh/__init__.py
starfysh/dataloader.py
starfysh/gener_img.py
starfysh/io.py
starfysh/plot_utils.py
starfysh/post_analysis.py
starfysh/starfysh.py
starfysh/utils.py
starfysh/utils_integrate.py
Starfysh-1.2.1.dist-info/LICENSE
Starfysh-1.2.1.dist-info/METADATA
Starfysh-1.2.1.dist-info/WHEEL
Starfysh-1.2.1.dist-info/dependency_links.txt
Starfysh-1.2.1.dist-info/top_level.txt
Starfysh-1.2.1.dist-info/RECORD
